python_topsis/ayush.py
python_topsis-1.0.1.dist-info/METADATA
python_topsis-1.0.1.dist-info/WHEEL
python_topsis-1.0.1.dist-info/top_level.txt
python_topsis-1.0.1.dist-info/RECORD
